{
    "signup":{
        "name": "James Rodriguez",
        "cpf": "00000001441",
        "email":"james@gmail.com",
        "number": "62982142744",
        "address": {
            "postalcode": "75083460",
            "street": "Rua Doutor Evandro Pinto Silva",
            "number": "20",
            "details": "Cidade Universit치ria",
            "district": "AP 23",
            "city_state": "An치polis/GO"
            },

            "deliver_method": "Moto",  
            "cnh":"CNH-E.png"

    },

    "cpf_invalido":{
        "name": "James Rodriguez",
        "cpf": "41",
        "email":"james@gmail.com",
        "number": "62982142744",
        "address": {
            "postalcode": "75083460",
            "street": "Rua Doutor Evandro Pinto Silva",
            "number": "20",
            "details": "Cidade Universit치ria",
            "district": "AP 23",
            "city_state": "An치polis/GO"
            },

            "deliver_method": "Moto",  
            "cnh":"CNH-E.png"

    }
}